example/__init__.py
example/args.py
example/example_consumer.py
example/example_cron_producer.py
example/example_csi.py
example/example_producer.py
example/brokers/__init__.py
example/brokers/kafka_broker.py
example/brokers/rmq_broker.py
example/brokers/uni_log_broker.py
example/messages/__init__.py
example/messages/ender_after_answer_message.py
example/messages/ender_after_cron_answer_message.py
example/messages/ender_after_cron_input_message.py
example/messages/ender_after_input_message.py
example/messages/input_message.py
example/messages/some_external_message.py
example/waitings/__init__.py
example/waitings/common_db_wating.py
example/workers/__init__.py
example/workers/auto_retry_worker.py
example/workers/ender_after_cron_worker.py
example/workers/ender_after_input_worker.py
example/workers/input_worker.py
example/workers/my_super_cron_worker.py
unipipeline/__init__.py
unipipeline/args.py
unipipeline/errors.py
unipipeline/main.py
unipipeline/py.typed
unipipeline/run.py
unipipeline/answer/__init__.py
unipipeline/answer/uni_answer_message.py
unipipeline/answer/uni_answer_params.py
unipipeline/brokers/__init__.py
unipipeline/brokers/uni_amqp_pika_broker.py
unipipeline/brokers/uni_amqp_py_broker.py
unipipeline/brokers/uni_broker.py
unipipeline/brokers/uni_broker_consumer.py
unipipeline/brokers/uni_kafka_broker.py
unipipeline/brokers/uni_log_broker.py
unipipeline/brokers/uni_memory_broker.py
unipipeline/config/__init__.py
unipipeline/config/uni_config.py
unipipeline/definitions/__init__.py
unipipeline/definitions/uni_broker_definition.py
unipipeline/definitions/uni_codec_definition.py
unipipeline/definitions/uni_cron_task_definition.py
unipipeline/definitions/uni_definition.py
unipipeline/definitions/uni_dynamic_definition.py
unipipeline/definitions/uni_external_definition.py
unipipeline/definitions/uni_message_definition.py
unipipeline/definitions/uni_module_definition.py
unipipeline/definitions/uni_service_definition.py
unipipeline-1.9.4.dist-info/LICENSE
unipipeline-1.9.4.dist-info/METADATA
unipipeline-1.9.4.dist-info/WHEEL
unipipeline-1.9.4.dist-info/entry_points.txt
unipipeline-1.9.4.dist-info/top_level.txt
unipipeline-1.9.4.dist-info/RECORD
